setup.py
django_directed_edge/__init__.py
django_directed_edge/api.py
django_directed_edge/app_settings.py
django_directed_edge/export.py
django_directed_edge/models.py
django_directed_edge/utils.py
django_directed_edge.egg-info/PKG-INFO
django_directed_edge.egg-info/SOURCES.txt
django_directed_edge.egg-info/dependency_links.txt
django_directed_edge.egg-info/requires.txt
django_directed_edge.egg-info/top_level.txt