Metadata-Version: 1.0
Name: django-directed-edge
Version: 2.0.2
Summary: Helpful Django-oriented sugar around around DirectedEdge's Python API
Home-page: https://chris-lamb.co.uk/projects/django-directed-edge
Author: Chris Lamb
Author-email: chris@chris-lamb.co.uk
License: UNKNOWN
Platform: UNKNOWN
